{
  "openapi": "3.0.1",
  "info": {
    "title": "WheaterApp.Server",
    "version": "1.0"
  },
  "paths": {
    "/api/Auth": {
      "post": {
        "tags": [
          "Auth"
        ],
        "requestBody": {
          "content": {
            "application/json": {
              "schema": {
                "$ref": "#/components/schemas/RegisterVM"
              }
            },
            "text/json": {
              "schema": {
                "$ref": "#/components/schemas/RegisterVM"
              }
            },
            "application/*+json": {
              "schema": {
                "$ref": "#/components/schemas/RegisterVM"
              }
            }
          }
        },
        "responses": {
          "200": {
            "description": "OK"
          }
        }
      }
    }
  },
  "components": {
    "schemas": {
      "RegisterVM": {
        "required": [
          "confirmPassword",
          "email",
          "password"
        ],
        "type": "object",
        "properties": {
          "email": {
            "minLength": 1,
            "type": "string",
            "format": "email"
          },
          "password": {
            "minLength": 1,
            "type": "string",
            "format": "password"
          },
          "confirmPassword": {
            "minLength": 1,
            "type": "string",
            "format": "password"
          }
        },
        "additionalProperties": false
      }
    }
  }
}